mcp_simple_pubmed/__init__.py
mcp_simple_pubmed/__main__.py
mcp_simple_pubmed/fulltext_client.py
mcp_simple_pubmed/pubmed_client.py
mcp_simple_pubmed/pubmed_fetch.py
mcp_simple_pubmed/pubmed_search.py
mcp_simple_pubmed/server.py
mseep_mcp_simple_pubmed-0.1.17.dist-info/licenses/LICENSE
mseep_mcp_simple_pubmed-0.1.17.dist-info/METADATA
mseep_mcp_simple_pubmed-0.1.17.dist-info/WHEEL
mseep_mcp_simple_pubmed-0.1.17.dist-info/entry_points.txt
mseep_mcp_simple_pubmed-0.1.17.dist-info/top_level.txt
mseep_mcp_simple_pubmed-0.1.17.dist-info/RECORD
